{
  "leaderboard": [
    {
      "rank": 1,
      "username": "u1",
      "wins": 4,
      "played": 9
    },
    {
      "rank": 2,
      "username": "u2",
      "wins": 3,
      "played": 10
    },
    {
      "rank": 3,
      "username": "p1",
      "wins": 1,
      "played": 1
    },
    {
      "rank": 3,
      "username": "t1766016710871_p1",
      "wins": 1,
      "played": 1
    },
    {
      "rank": 3,
      "username": "t1766017117275_p1",
      "wins": 1,
      "played": 1
    },
    {
      "rank": 3,
      "username": "t1766017579430_p1",
      "wins": 1,
      "played": 1
    },
    {
      "rank": 3,
      "username": "t1766017627880_p1",
      "wins": 1,
      "played": 1
    },
    {
      "rank": 3,
      "username": "t1766017673730_p1",
      "wins": 1,
      "played": 1
    },
    {
      "rank": 3,
      "username": "t1766017819727_p1",
      "wins": 1,
      "played": 1
    },
    {
      "rank": 3,
      "username": "t1766017897099_p1",
      "wins": 1,
      "played": 1
    },
    {
      "rank": 3,
      "username": "t1766018020877_p1",
      "wins": 1,
      "played": 1
    },
    {
      "rank": 3,
      "username": "t1766018062228_p1",
      "wins": 1,
      "played": 1
    },
    {
      "rank": 3,
      "username": "t1766018102955_p1",
      "wins": 1,
      "played": 1
    },
    {
      "rank": 3,
      "username": "t1766018129177_p1",
      "wins": 1,
      "played": 1
    },
    {
      "rank": 3,
      "username": "t1766018272506_p1",
      "wins": 1,
      "played": 1
    },
    {
      "rank": 3,
      "username": "t1766018314910_p1",
      "wins": 1,
      "played": 1
    },
    {
      "rank": 3,
      "username": "t1766019163346_p1",
      "wins": 1,
      "played": 1
    },
    {
      "rank": 18,
      "username": "alice",
      "wins": 0,
      "played": 0
    },
    {
      "rank": 18,
      "username": "dev1",
      "wins": 0,
      "played": 0
    },
    {
      "rank": 18,
      "username": "dev2",
      "wins": 0,
      "played": 0
    },
    {
      "rank": 18,
      "username": "rv_admin",
      "wins": 0,
      "played": 0
    },
    {
      "rank": 18,
      "username": "t1766016710886_alice",
      "wins": 0,
      "played": 0
    },
    {
      "rank": 18,
      "username": "t1766017117290_alice",
      "wins": 0,
      "played": 0
    },
    {
      "rank": 18,
      "username": "t1766017579447_alice",
      "wins": 0,
      "played": 0
    },
    {
      "rank": 18,
      "username": "t1766017627897_alice",
      "wins": 0,
      "played": 0
    },
    {
      "rank": 18,
      "username": "t1766017673747_alice",
      "wins": 0,
      "played": 0
    },
    {
      "rank": 18,
      "username": "t1766017819743_alice",
      "wins": 0,
      "played": 0
    },
    {
      "rank": 18,
      "username": "t1766017897118_alice",
      "wins": 0,
      "played": 0
    },
    {
      "rank": 18,
      "username": "t1766018020897_alice",
      "wins": 0,
      "played": 0
    },
    {
      "rank": 18,
      "username": "t1766018062247_alice",
      "wins": 0,
      "played": 0
    },
    {
      "rank": 18,
      "username": "t1766018102973_alice",
      "wins": 0,
      "played": 0
    },
    {
      "rank": 18,
      "username": "t1766018129195_alice",
      "wins": 0,
      "played": 0
    },
    {
      "rank": 18,
      "username": "t1766018272529_alice",
      "wins": 0,
      "played": 0
    },
    {
      "rank": 18,
      "username": "t1766018314932_alice",
      "wins": 0,
      "played": 0
    },
    {
      "rank": 18,
      "username": "t1766019163369_alice",
      "wins": 0,
      "played": 0
    },
    {
      "rank": 18,
      "username": "test1",
      "wins": 0,
      "played": 0
    },
    {
      "rank": 18,
      "username": "user1",
      "wins": 0,
      "played": 0
    },
    {
      "rank": 18,
      "username": "user2",
      "wins": 0,
      "played": 0
    },
    {
      "rank": 18,
      "username": "p2",
      "wins": 0,
      "played": 1
    },
    {
      "rank": 18,
      "username": "rv_player",
      "wins": 0,
      "played": 1
    },
    {
      "rank": 18,
      "username": "t1766016710871_p2",
      "wins": 0,
      "played": 1
    },
    {
      "rank": 18,
      "username": "t1766017117275_p2",
      "wins": 0,
      "played": 1
    },
    {
      "rank": 18,
      "username": "t1766017579430_p2",
      "wins": 0,
      "played": 1
    },
    {
      "rank": 18,
      "username": "t1766017627880_p2",
      "wins": 0,
      "played": 1
    },
    {
      "rank": 18,
      "username": "t1766017673730_p2",
      "wins": 0,
      "played": 1
    },
    {
      "rank": 18,
      "username": "t1766017819727_p2",
      "wins": 0,
      "played": 1
    },
    {
      "rank": 18,
      "username": "t1766017897099_p2",
      "wins": 0,
      "played": 1
    },
    {
      "rank": 18,
      "username": "t1766018020877_p2",
      "wins": 0,
      "played": 1
    },
    {
      "rank": 18,
      "username": "t1766018062228_p2",
      "wins": 0,
      "played": 1
    },
    {
      "rank": 18,
      "username": "t1766018102955_p2",
      "wins": 0,
      "played": 1
    },
    {
      "rank": 18,
      "username": "t1766018129177_p2",
      "wins": 0,
      "played": 1
    },
    {
      "rank": 18,
      "username": "t1766018272506_p2",
      "wins": 0,
      "played": 1
    },
    {
      "rank": 18,
      "username": "t1766018314910_p2",
      "wins": 0,
      "played": 1
    },
    {
      "rank": 18,
      "username": "t1766019163346_p2",
      "wins": 0,
      "played": 1
    },
    {
      "rank": 18,
      "username": "u3",
      "wins": 0,
      "played": 1
    }
  ]
}